adder.t.v
// Adder testbench
`timescale 1 ns / 1 ps
`include "adder.v"

module testFullAdder();
    reg a, b, carryin;
    wire sum, carryout;

    // behavioralFullAdder adder (sum, carryout, a, b, carryin);
    structuralFullAdder adder (sum, carryout, a, b, carryin);

    initial begin
        // Your test code here
        $dumpfile("adder.vcd");
        $dumpvars();
        $display("Structural Full Adder Truth Table");
        $display("a b Cin|sum Cout|Expected Output");
        a=0;b=0;carryin=0; #1000
        $display("%b %b  %b | %b   %b  | 0  0", a, b, carryin, sum, carryout);
        a=0;b=0;carryin=1; #1000
        $display("%b %b  %b | %b   %b  | 1  0", a, b, carryin, sum, carryout);
        a=0;b=1;carryin=0; #1000
        $display("%b %b  %b | %b   %b  | 1  0", a, b, carryin, sum, carryout);
        a=0;b=1;carryin=1; #1000
        $display("%b %b  %b | %b   %b  | 0  1", a, b, carryin, sum, carryout);
        a=1;b=0;carryin=0; #1000
        $display("%b %b  %b | %b   %b  | 1  0", a, b, carryin, sum, carryout);
        a=1;b=0;carryin=1; #1000
        $display("%b %b  %b | %b   %b  | 0  1", a, b, carryin, sum, carryout);
        a=1;b=1;carryin=0; #1000
        $display("%b %b  %b | %b   %b  | 0  1", a, b, carryin, sum, carryout);
        a=1;b=1;carryin=1; #1000
        $display("%b %b  %b | %b   %b  | 1  1", a, b, carryin, sum, carryout);
        $finish();
    end
endmodule

adder.v
// define gates with delays
`define AND and #50
`define OR or #50
`define NOT not #50
`define NAND nand #50
`define NOR nor #50
`define XOR xor #50

// Adder circuit

module behavioralFullAdder
(
    output sum,
    output carryout,
    input a,
    input b,
    input carryin
);
    // Uses concatenation operator and built-in '+'
    assign {carryout, sum}=a+b+carryin;
endmodule

module structuralFullAdder
(
    output sum,
    output carryout,
    input a,
    input b,
    input carryin
);
    // Your adder code here
    wire xorab;
    wire andab, andc;

    `XOR xorgate0(xorab, a, b);
    `XOR xorgate1(sum, xorab, carryin);

    `AND andgate0(andab, a, b);
    `AND andgate1(andc, xorab, carryin);
    `OR orgate(carryout, andab, andc);
endmodule

adder.vcd
$date
	Wed Sep 19 18:42:04 2018
$end
$version
	Icarus Verilog
$end
$timescale
	1ps
$end
$scope module behavioralFullAdder $end
$var wire 1 ! a $end
$var wire 1 " b $end
$var wire 1 # carryin $end
$var wire 1 $ sum $end
$var wire 1 % carryout $end
$upscope $end
$scope module testFullAdder $end
$var wire 1 & sum $end
$var wire 1 ' carryout $end
$var reg 1 ( a $end
$var reg 1 ) b $end
$var reg 1 * carryin $end
$scope module adder $end
$var wire 1 ( a $end
$var wire 1 + andab $end
$var wire 1 , andc $end
$var wire 1 ) b $end
$var wire 1 * carryin $end
$var wire 1 ' carryout $end
$var wire 1 & sum $end
$var wire 1 - xorab $end
$upscope $end
$upscope $end
$enddefinitions $end
#0
$dumpvars
x-
x,
x+
0*
0)
0(
x'
x&
x%
x$
z#
z"
z!
$end
#50000
0,
0+
0-
#100000
0'
0&
#1000000
1*
#1050000
1&
#2000000
0*
1)
#2050000
0&
1-
#2100000
1&
#3000000
1*
#3050000
0&
1,
#3100000
1'
#4000000
0*
0)
1(
#4050000
1&
0,
#4100000
0'
#5000000
1*
#5050000
0&
1,
#5100000
1'
#6000000
0*
1)
#6050000
1&
0,
0-
1+
#6100000
0&
#7000000
1*
#7050000
1&
