decoder.t.v
// Decoder testbench
`timescale 1 ns / 1 ps
`include "decoder.v"

module testDecoder ();
    reg addr0, addr1;
    reg enable;
    wire out0,out1,out2,out3;

    // behavioralDecoder decoder (out0,out1,out2,out3,addr0,addr1,enable);
    structuralDecoder decoder (out0,out1,out2,out3,addr0,addr1,enable); // Swap after testing

    initial begin
    $dumpfile("decoder.vcd");
    $dumpvars();
    $display("Structural Decoder Truth Table");
    $display("En A0 A1| O0 O1 O2 O3 | Expected Output");
    enable=0;addr0=0;addr1=0; #1000
    $display("%b  %b  %b |  %b  %b  %b  %b | All false", enable, addr0, addr1, out0, out1, out2, out3);
    enable=0;addr0=1;addr1=0; #1000
    $display("%b  %b  %b |  %b  %b  %b  %b | All false", enable, addr0, addr1, out0, out1, out2, out3);
    enable=0;addr0=0;addr1=1; #1000
    $display("%b  %b  %b |  %b  %b  %b  %b | All false", enable, addr0, addr1, out0, out1, out2, out3);
    enable=0;addr0=1;addr1=1; #1000
    $display("%b  %b  %b |  %b  %b  %b  %b | All false", enable, addr0, addr1, out0, out1, out2, out3);
    enable=1;addr0=0;addr1=0; #1000
    $display("%b  %b  %b |  %b  %b  %b  %b | O0 Only", enable, addr0, addr1, out0, out1, out2, out3);
    enable=1;addr0=1;addr1=0; #1000
    $display("%b  %b  %b |  %b  %b  %b  %b | O1 Only", enable, addr0, addr1, out0, out1, out2, out3);
    enable=1;addr0=0;addr1=1; #1000
    $display("%b  %b  %b |  %b  %b  %b  %b | O2 Only", enable, addr0, addr1, out0, out1, out2, out3);
    enable=1;addr0=1;addr1=1; #1000
    $display("%b  %b  %b |  %b  %b  %b  %b | O3 Only", enable, addr0, addr1, out0, out1, out2, out3);
    $finish();
    end

endmodule

decoder.v
// define gates with delays
`define AND and #50
`define OR or #50
`define NOT not #50
`define NAND nand #50
`define NOR nor #50
`define XOR xor #50

// Decoder circuit

module behavioralDecoder
(
    output out0, out1, out2, out3,
    input address0, address1,
    input enable
);
    // Uses concatenation and shift operators
    assign {out3,out2,out1,out0}=enable<<{address1,address0};
endmodule


module structuralDecoder
(
    output out0, out1, out2, out3,
    input address0, address1,
    input enable
);
    // Your decoder code here
    wire preout0;
    wire preout1;
    wire preout2;
    wire preout3;
    wire naddr0;
    wire naddr1;

    `NOT addr0inv(naddr0, address0);
    `NOT addr1inv(naddr1, address1);

    // Produce output according to input addresses
    `AND preout0gate(preout0, naddr0, naddr1);
    `AND preout1gate(preout1, address0, naddr1);
    `AND preout2gate(preout2, naddr0, address1);
    `AND preout3gate(preout3, address0, address1);

    // check ENABLE status
    `AND out0gate(out0, preout0, enable);
    `AND out1gate(out1, preout1, enable);
    `AND out2gate(out2, preout2, enable);
    `AND out3gate(out3, preout3, enable);

endmodule

decoder.vcd
$date
	Wed Sep 19 18:40:23 2018
$end
$version
	Icarus Verilog
$end
$timescale
	1ps
$end
$scope module behavioralDecoder $end
$var wire 1 ! address0 $end
$var wire 1 " address1 $end
$var wire 1 # enable $end
$var wire 1 $ out3 $end
$var wire 1 % out2 $end
$var wire 1 & out1 $end
$var wire 1 ' out0 $end
$upscope $end
$scope module testDecoder $end
$var wire 1 ( out3 $end
$var wire 1 ) out2 $end
$var wire 1 * out1 $end
$var wire 1 + out0 $end
$var reg 1 , addr0 $end
$var reg 1 - addr1 $end
$var reg 1 . enable $end
$scope module decoder $end
$var wire 1 , address0 $end
$var wire 1 - address1 $end
$var wire 1 . enable $end
$var wire 1 / naddr0 $end
$var wire 1 0 naddr1 $end
$var wire 1 + out0 $end
$var wire 1 * out1 $end
$var wire 1 ) out2 $end
$var wire 1 ( out3 $end
$var wire 1 1 preout0 $end
$var wire 1 2 preout1 $end
$var wire 1 3 preout2 $end
$var wire 1 4 preout3 $end
$upscope $end
$upscope $end
$enddefinitions $end
#0
$dumpvars
x4
x3
x2
x1
x0
x/
0.
0-
0,
x+
x*
x)
x(
x'
x&
x%
x$
z#
z"
z!
$end
#50000
10
1/
0(
0)
0*
0+
04
03
02
#100000
11
#1000000
1,
#1050000
0/
12
#1100000
01
#2000000
1-
0,
#2050000
00
1/
02
#2100000
13
#3000000
1,
#3050000
0/
14
#3100000
03
#4000000
0-
0,
1.
#4050000
10
1/
04
1(
#4100000
11
0(
#4150000
1+
#5000000
1,
#5050000
0/
12
#5100000
01
1*
#5150000
0+
#6000000
1-
0,
#6050000
00
1/
02
#6100000
13
0*
#6150000
1)
#7000000
1,
#7050000
0/
14
#7100000
03
1(
#7150000
0)
